cometblue_asyncio/__init__.py
cometblue_asyncio/_version.py
cometblue_asyncio/cometblue.py
cometblue_asyncio/interface.py
cometblue_asyncio/logdirect.py
cometblue_asyncio-0.9.2.dist-info/LICENSE
cometblue_asyncio-0.9.2.dist-info/METADATA
cometblue_asyncio-0.9.2.dist-info/WHEEL
cometblue_asyncio-0.9.2.dist-info/top_level.txt
cometblue_asyncio-0.9.2.dist-info/RECORD
