Metadata-Version: 2.1
Name: cometblue-asyncio
Version: 0.9.2
Summary: Python library for interacting with the Eurotronic Comet Blue thermostatic radiator valve based on bleak using asyncio.
Author-email: Pavel Krc <src@pkrc.net>
Project-URL: Homepage, https://github.com/rolicot/cometblue-asyncio
Classifier: Programming Language :: Python :: 3.7
Classifier: License :: OSI Approved :: MIT License
Classifier: Operating System :: POSIX :: Linux
Classifier: Operating System :: MacOS :: MacOS X
Classifier: Operating System :: Microsoft :: Windows :: Windows 10
Classifier: Development Status :: 4 - Beta
Requires-Python: >=3.7
License-File: LICENSE
Requires-Dist: bleak
